setup.py
src/yaul/__init__.py
src/yaul/cache.py
src/yaul/init.py
src/yaul/iterator.py
src/yaul/linuxdaemon.py
src/yaul/parallel.py
src/yaul.egg-info/PKG-INFO
src/yaul.egg-info/SOURCES.txt
src/yaul.egg-info/dependency_links.txt
src/yaul.egg-info/requires.txt
src/yaul.egg-info/top_level.txt