Metadata-Version: 1.0
Name: yaul
Version: 0.4.4
Summary: Yet Another Utility Library
Home-page: https://github.com/fsufitch/YAUL
Author: Filip Sufitchi
Author-email: fsufitchi@gmail.com
License: UNKNOWN
Platform: UNKNOWN
